Workbook
Name Slicer_YEAR: #N/A

Sheet Consumer_Complaints
A1: Complaint ID | B1: Company | C1: Product | D1: Issue | E1: State | F1: Submitted via | G1: Date received | H1: Date resolved | I1: Timely response? | J1: Consumer disputed? | K1: State_Name | L1: Resolution_Time | M1: YEAR | N1: QTR
A2: 1615767 | B2: PHH Mortgage | C2: Mortgage | D2: Loan servicing, payments, escrow account | E2: FL | F2: Web | G2: 42297 | H2: 42297 | I2: Yes | J2: No | K2: =INDEX(State_Code_Name!B:B,MATCH(Consumer_Complaints!E2,State_Code_Name!C:C,0)) -> Florida | L2: =H2-G2 -> 0 | M2: =YEAR(G2) -> 2015 | N2: =IF(MONTH(G2)<=3,"Q1",IF(MONTH(G2)<=6,"Q2",IF(MONTH(G2)<=9,"Q3","Q4"))) -> Q4
A3: 654223 | B3: Ocwen | C3: Mortgage | D3: Loan servicing, payments, escrow account | E3: NC | F3: Web | G3: 41699 | H3: 41699 | I3: Yes | J3: No | K3: =INDEX(State_Code_Name!B:B,MATCH(Consumer_Complaints!E3,State_Code_Name!C:C,0)) -> North Carolina | L3: =H3-G3 -> 0 | M3: =YEAR(G3) -> 2014 | N3: =IF(MONTH(G3)<=3,"Q1",IF(MONTH(G3)<=6,"Q2",IF(MONTH(G3)<=9,"Q3","Q4"))) -> Q1
A4: 1143398 | B4: Southwest Credit Systems, L.P. | C4: Debt collection | D4: Loan modification,collection,foreclosure | E4: MO | F4: Web | G4: 41741 | H4: 41741 | I4: Yes | J4: No | K4: =INDEX(State_Code_Name!B:B,MATCH(Consumer_Complaints!E4,State_Code_Name!C:C,0)) -> Missouri | L4: =H4-G4 -> 0 | M4: =YEAR(G4) -> 2014 | N4: =IF(MONTH(G4)<=3,"Q1",IF(MONTH(G4)<=6,"Q2",IF(MONTH(G4)<=9,"Q3","Q4"))) -> Q2
A5: 1303679 | B5: Continental Finance Company, LLC | C5: Credit card | D5: Billing statement | E5: WA | F5: Web | G5: 42089 | H5: 42089 | I5: Yes | J5: No | K5: =INDEX(State_Code_Name!B:B,MATCH(Consumer_Complaints!E5,State_Code_Name!C:C,0)) -> Washington | L5: =H5-G5 -> 0 | M5: =YEAR(G5) -> 2015 | N5: =IF(MONTH(G5)<=3,"Q1",IF(MONTH(G5)<=6,"Q2",IF(MONTH(G5)<=9,"Q3","Q4"))) -> Q1
A6: 1627370 | B6: Experian | C6: Credit reporting | D6: Unable to get credit report/credit score | E6: VA | F6: Web | G6: 42304 | H6: 42304 | I6: Yes | J6: No | K6: =INDEX(State_Code_Name!B:B,MATCH(Consumer_Complaints!E6,State_Code_Name!C:C,0)) -> Virginia | L6: =H6-G6 -> 0 | M6: =YEAR(G6) -> 2015 | N6: =IF(MONTH(G6)<=3,"Q1",IF(MONTH(G6)<=6,"Q2",IF(MONTH(G6)<=9,"Q3","Q4"))) -> Q4
A7: 1390231 | B7: Encore Capital Group | C7: Debt collection | D7: False statements or representation | E7: IL | F7: Web | G7: 42147 | H7: 42147 | I7: Yes | J7: No | K7: =INDEX(State_Code_Name!B:B,MATCH(Consumer_Complaints!E7,State_Code_Name!C:C,0)) -> Illinois | L7: =H7-G7 -> 0 | M7: =YEAR(G7) -> 2015 | N7: =IF(MONTH(G7)<=3,"Q1",IF(MONTH(G7)<=6,"Q2",IF(MONTH(G7)<=9,"Q3","Q4"))) -> Q2
A8: 1946542 | B8: Regions Financial Corporation | C8: Mortgage | D8: Application, originator, mortgage broker | E8: FL | F8: Web | G8: 42520 | H8: 42521 | I8: Yes | J8: No | K8: =INDEX(State_Code_Name!B:B,MATCH(Consumer_Complaints!E8,State_Code_Name!C:C,0)) -> Florida | L8: =H8-G8 -> 1 | M8: =YEAR(G8) -> 2016 | N8: =IF(MONTH(G8)<=3,"Q1",IF(MONTH(G8)<=6,"Q2",IF(MONTH(G8)<=9,"Q3","Q4"))) -> Q2
A9: 1414270 | B9: AES/PHEAA | C9: Student loan | D9: Dealing with my lender or servicer | E9: OK | F9: Web | G9: 42283 | H9: 42283 | I9: Yes | J9: No | K9: =INDEX(State_Code_Name!B:B,MATCH(Consumer_Complaints!E9,State_Code_Name!C:C,0)) -> Oklahoma | L9: =H9-G9 -> 0 | M9: =YEAR(G9) -> 2015 | N9: =IF(MONTH(G9)<=3,"Q1",IF(MONTH(G9)<=6,"Q2",IF(MONTH(G9)<=9,"Q3","Q4"))) -> Q4
A10: 310830 | B10: JPMorgan Chase & Co. | C10: Credit card | D10: Credit reporting | E10: CA | F10: Web | G10: 41488 | H10: 41488 | I10: Yes | J10: No | K10: =INDEX(State_Code_Name!B:B,MATCH(Consumer_Complaints!E10,State_Code_Name!C:C,0)) -> California | L10: =H10-G10 -> 0 | M10: =YEAR(G10) -> 2013 | N10: =IF(MONTH(G10)<=3,"Q1",IF(MONTH(G10)<=6,"Q2",IF(MONTH(G10)<=9,"Q3","Q4"))) -> Q3
A11: 1734499 | B11: Equifax | C11: Credit reporting | D11: Credit reporting company's investigation | E11: CA | F11: Web | G11: 42583 | H11: 42583 | I11: Yes | J11: No | K11: =INDEX(State_Code_Name!B:B,MATCH(Consumer_Complaints!E11,State_Code_Name!C:C,0)) -> California | L11: =H11-G11 -> 0 | M11: =YEAR(G11) -> 2016 | N11: =IF(MONTH(G11)<=3,"Q1",IF(MONTH(G11)<=6,"Q2",IF(MONTH(G11)<=9,"Q3","Q4"))) -> Q3
A12: 1744309 | B12: JPMorgan Chase & Co. | C12: Bank account or service | D12: Deposits and withdrawals | E12: AZ | F12: Email | G12: 42384 | H12: 42389 | I12: Yes | J12: No | K12: =INDEX(State_Code_Name!B:B,MATCH(Consumer_Complaints!E12,State_Code_Name!C:C,0)) -> Arizona | L12: =H12-G12 -> 5 | M12: =YEAR(G12) -> 2016 | N12: =IF(MONTH(G12)<=3,"Q1",IF(MONTH(G12)<=6,"Q2",IF(MONTH(G12)<=9,"Q3","Q4"))) -> Q1
A13: 1154103 | B13: Bank of America | C13: Credit card | D13: Rewards | E13: MO | F13: Web | G13: 41985 | H13: 41985 | I13: Yes | J13: No | K13: =INDEX(State_Code_Name!B:B,MATCH(Consumer_Complaints!E13,State_Code_Name!C:C,0)) -> Missouri | L13: =H13-G13 -> 0 | M13: =YEAR(G13) -> 2014 | N13: =IF(MONTH(G13)<=3,"Q1",IF(MONTH(G13)<=6,"Q2",IF(MONTH(G13)<=9,"Q3","Q4"))) -> Q4
... A173: 707306 | B173: Navient Solutions, Inc. | C173: Student loan | D173: Dealing with my lender or servicer | E173: FL | F173: Email | G173: 41914 | H173: 41945 | I173: Yes | J173: Yes | K173: =INDEX(State_Code_Name!B:B,MATCH(Consumer_Complaints!E173,State_Code_Name!C:C,0)) -> Florida | L173: =H173-G173 -> 31 | M173: =YEAR(G173) -> 2014 | N173: =IF(MONTH(G173)<=3,"Q1",IF(MONTH(G173)<=6,"Q2",IF(MONTH(G173)<=9,"Q3","Q4"))) -> Q4
A174: 1328578 | B174: Banco Popular de Puerto Rico | C174: Bank account or service | D174: Deposits and withdrawals | F174: Email | G174: 42108 | H174: 42115 | I174: Yes | J174: No | K174: =INDEX(State_Code_Name!B:B,MATCH(Consumer_Complaints!E174,State_Code_Name!C:C,0)) -> #N/A | L174: =H174-G174 -> 7 | M174: =YEAR(G174) -> 2015 | N174: =IF(MONTH(G174)<=3,"Q1",IF(MONTH(G174)<=6,"Q2",IF(MONTH(G174)<=9,"Q3","Q4"))) -> Q2
A175: 1741675 | B175: Associated Bank | C175: Bank account or service | D175: Account opening, closing, or management | E175: WI | F175: Phone | G175: 42383 | H175: 42389 | I175: Yes | J175: No | K175: =INDEX(State_Code_Name!B:B,MATCH(Consumer_Complaints!E175,State_Code_Name!C:C,0)) -> Wisconsin | L175: =H175-G175 -> 6 | M175: =YEAR(G175) -> 2016 | N175: =IF(MONTH(G175)<=3,"Q1",IF(MONTH(G175)<=6,"Q2",IF(MONTH(G175)<=9,"Q3","Q4"))) -> Q1
A176: 900637 | B176: Capital One | C176: Credit card | D176: Identity theft / Fraud / Embezzlement | E176: GA | F176: Web | G176: 41808 | H176: 41810 | I176: Yes | J176: Yes | K176: =INDEX(State_Code_Name!B:B,MATCH(Consumer_Complaints!E176,State_Code_Name!C:C,0)) -> Georgia | L176: =H176-G176 -> 2 | M176: =YEAR(G176) -> 2014 | N176: =IF(MONTH(G176)<=3,"Q1",IF(MONTH(G176)<=6,"Q2",IF(MONTH(G176)<=9,"Q3","Q4"))) -> Q2
A177: 2086524 | B177: Synchrony Financial | C177: Credit card | D177: Unsolicited issuance of credit card | E177: NY | F177: Web | G177: 42611 | H177: 42611 | I177: Yes | J177: No | K177: =INDEX(State_Code_Name!B:B,MATCH(Consumer_Complaints!E177,State_Code_Name!C:C,0)) -> New York | L177: =H177-G177 -> 0 | M177: =YEAR(G177) -> 2016 | N177: =IF(MONTH(G177)<=3,"Q1",IF(MONTH(G177)<=6,"Q2",IF(MONTH(G177)<=9,"Q3","Q4"))) -> Q3
A178: 1790269 | B178: NCSPLUS INCORPORATED | C178: Debt collection | D178: Loan modification,collection,foreclosure | E178: OH | F178: Web | G178: 42418 | H178: 42418 | I178: Yes | J178: No | K178: =INDEX(State_Code_Name!B:B,MATCH(Consumer_Complaints!E178,State_Code_Name!C:C,0)) -> Ohio | L178: =H178-G178 -> 0 | M178: =YEAR(G178) -> 2016 | N178: =IF(MONTH(G178)<=3,"Q1",IF(MONTH(G178)<=6,"Q2",IF(MONTH(G178)<=9,"Q3","Q4"))) -> Q1
A179: 2005535 | B179: Big Picture Loans, LLC | C179: Payday loan | D179: Charged fees or interest I didn't expect | E179: IN | F179: Web | G179: 42681 | H179: 42681 | I179: Yes | J179: No | K179: =INDEX(State_Code_Name!B:B,MATCH(Consumer_Complaints!E179,State_Code_Name!C:C,0)) -> Indiana | L179: =H179-G179 -> 0 | M179: =YEAR(G179) -> 2016 | N179: =IF(MONTH(G179)<=3,"Q1",IF(MONTH(G179)<=6,"Q2",IF(MONTH(G179)<=9,"Q3","Q4"))) -> Q4
A180: 555665 | B180: Wells Fargo & Company | C180: Mortgage | D180: Loan servicing, payments, escrow account | E180: GA | F180: Web | G180: 41496 | H180: 41527 | I180: Yes | J180: No | K180: =INDEX(State_Code_Name!B:B,MATCH(Consumer_Complaints!E180,State_Code_Name!C:C,0)) -> Georgia | L180: =H180-G180 -> 31 | M180: =YEAR(G180) -> 2013 | N180: =IF(MONTH(G180)<=3,"Q1",IF(MONTH(G180)<=6,"Q2",IF(MONTH(G180)<=9,"Q3","Q4"))) -> Q3
A181: 481253 | B181: Bank of America | C181: Mortgage | D181: Loan servicing, payments, escrow account | E181: NH | F181: Web | G181: 41433 | H181: 41463 | I181: Yes | J181: No | K181: =INDEX(State_Code_Name!B:B,MATCH(Consumer_Complaints!E181,State_Code_Name!C:C,0)) -> New Hampshire | L181: =H181-G181 -> 30 | M181: =YEAR(G181) -> 2013 | N181: =IF(MONTH(G181)<=3,"Q1",IF(MONTH(G181)<=6,"Q2",IF(MONTH(G181)<=9,"Q3","Q4"))) -> Q2
A182: 1420515 | B182: United Shore Financial Services, LLC | C182: Mortgage | D182: Loan servicing, payments, escrow account | E182: FL | F182: Web | G182: 42169 | H182: 42169 | I182: Yes | J182: No | K182: =INDEX(State_Code_Name!B:B,MATCH(Consumer_Complaints!E182,State_Code_Name!C:C,0)) -> Florida | L182: =H182-G182 -> 0 | M182: =YEAR(G182) -> 2015 | N182: =IF(MONTH(G182)<=3,"Q1",IF(MONTH(G182)<=6,"Q2",IF(MONTH(G182)<=9,"Q3","Q4"))) -> Q2
A183: 1606563 | B183: AES/PHEAA | C183: Student loan | D183: Can't repay my loan | E183: WA | F183: Email | G183: 42291 | H183: 42293 | I183: Yes | J183: No | K183: =INDEX(State_Code_Name!B:B,MATCH(Consumer_Complaints!E183,State_Code_Name!C:C,0)) -> Washington | L183: =H183-G183 -> 2 | M183: =YEAR(G183) -> 2015 | N183: =IF(MONTH(G183)<=3,"Q1",IF(MONTH(G183)<=6,"Q2",IF(MONTH(G183)<=9,"Q3","Q4"))) -> Q4
A184: 854592 | B184: AES/PHEAA | C184: Student loan | D184: Dealing with my lender or servicer | E184: VA | F184: Phone | G184: 41774 | H184: 41778 | I184: Yes | J184: No | K184: =INDEX(State_Code_Name!B:B,MATCH(Consumer_Complaints!E184,State_Code_Name!C:C,0)) -> Virginia | L184: =H184-G184 -> 4 | M184: =YEAR(G184) -> 2014 | N184: =IF(MONTH(G184)<=3,"Q1",IF(MONTH(G184)<=6,"Q2",IF(MONTH(G184)<=9,"Q3","Q4"))) -> Q2
A185: 859984 | B185: Enova International, Inc. | C185: Payday loan | D185: Applied for loan/did not receive money | E185: CA | F185: Web | G185: 41779 | H185: 41779 | I185: Yes | J185: No | K185: =INDEX(State_Code_Name!B:B,MATCH(Consumer_Complaints!E185,State_Code_Name!C:C,0)) -> California | L185: =H185-G185 -> 0 | M185: =YEAR(G185) -> 2014 | N185: =IF(MONTH(G185)<=3,"Q1",IF(MONTH(G185)<=6,"Q2",IF(MONTH(G185)<=9,"Q3","Q4"))) -> Q2
A186: 222470 | B186: Wells Fargo & Company | C186: Mortgage | D186: Loan servicing, payments, escrow account | E186: FL | F186: Postal mail | G186: 41365 | H186: 41456 | I186: Yes | J186: Yes | K186: =INDEX(State_Code_Name!B:B,MATCH(Consumer_Complaints!E186,State_Code_Name!C:C,0)) -> Florida | L186: =H186-G186 -> 91 | M186: =YEAR(G186) -> 2013 | N186: =IF(MONTH(G186)<=3,"Q1",IF(MONTH(G186)<=6,"Q2",IF(MONTH(G186)<=9,"Q3","Q4"))) -> Q2
... A233: 1371702 | B233: Valentine and Kebartas, Inc. | C233: Debt collection | D233: Loan modification,collection,foreclosure | E233: LA | F233: Web | G233: 42343 | H233: 42343 | I233: Yes | J233: No | K233: =INDEX(State_Code_Name!B:B,MATCH(Consumer_Complaints!E233,State_Code_Name!C:C,0)) -> Louisiana | L233: =H233-G233 -> 0 | M233: =YEAR(G233) -> 2015 | N233: =IF(MONTH(G233)<=3,"Q1",IF(MONTH(G233)<=6,"Q2",IF(MONTH(G233)<=9,"Q3","Q4"))) -> Q4
A234: 450307 | B234: Ditech Financial LLC | C234: Mortgage | D234: Loan servicing, payments, escrow account | F234: Web | G234: 41432 | H234: 41493 | I234: Yes | J234: Yes | K234: =INDEX(State_Code_Name!B:B,MATCH(Consumer_Complaints!E234,State_Code_Name!C:C,0)) -> #N/A | L234: =H234-G234 -> 61 | M234: =YEAR(G234) -> 2013 | N234: =IF(MONTH(G234)<=3,"Q1",IF(MONTH(G234)<=6,"Q2",IF(MONTH(G234)<=9,"Q3","Q4"))) -> Q2
A235: 414197 | B235: Wells Fargo & Company | C235: Mortgage | D235: Credit decision / Underwriting | E235: NE | F235: Web | G235: 41416 | H235: 41417 | I235: Yes | J235: Yes | K235: =INDEX(State_Code_Name!B:B,MATCH(Consumer_Complaints!E235,State_Code_Name!C:C,0)) -> Nebraska | L235: =H235-G235 -> 1 | M235: =YEAR(G235) -> 2013 | N235: =IF(MONTH(G235)<=3,"Q1",IF(MONTH(G235)<=6,"Q2",IF(MONTH(G235)<=9,"Q3","Q4"))) -> Q2
A236: 1394214 | B236: JPMorgan Chase & Co. | C236: Credit card | D236: Billing disputes | E236: IL | F236: Phone | G236: 42151 | H236: 42153 | I236: Yes | J236: Yes | K236: =INDEX(State_Code_Name!B:B,MATCH(Consumer_Complaints!E236,State_Code_Name!C:C,0)) -> Illinois | L236: =H236-G236 -> 2 | M236: =YEAR(G236) -> 2015 | N236: =IF(MONTH(G236)<=3,"Q1",IF(MONTH(G236)<=6,"Q2",IF(MONTH(G236)<=9,"Q3","Q4"))) -> Q2
A237: 1984786 | B237: Citibank | C237: Credit card | D237: Billing disputes | E237: NV | F237: Web | G237: 42545 | H237: 42545 | I237: Yes | J237: No | K237: =INDEX(State_Code_Name!B:B,MATCH(Consumer_Complaints!E237,State_Code_Name!C:C,0)) -> Nevada | L237: =H237-G237 -> 0 | M237: =YEAR(G237) -> 2016 | N237: =IF(MONTH(G237)<=3,"Q1",IF(MONTH(G237)<=6,"Q2",IF(MONTH(G237)<=9,"Q3","Q4"))) -> Q2
A238: 767081 | B238: Advance America, Cash Advance Centers, Inc. | C238: Debt collection | D238: Taking/threatening an illegal action | E238: TX | F238: Web | G238: 41946 | H238: 41946 | I238: Yes | J238: No | K238: =INDEX(State_Code_Name!B:B,MATCH(Consumer_Complaints!E238,State_Code_Name!C:C,0)) -> Texas | L238: =H238-G238 -> 0 | M238: =YEAR(G238) -> 2014 | N238: =IF(MONTH(G238)<=3,"Q1",IF(MONTH(G238)<=6,"Q2",IF(MONTH(G238)<=9,"Q3","Q4"))) -> Q4
A239: 2020879 | B239: Select Portfolio Servicing, Inc | C239: Mortgage | D239: Loan servicing, payments, escrow account | E239: MA | F239: Web | G239: 42571 | H239: 42571 | I239: Yes | J239: Yes | K239: =INDEX(State_Code_Name!B:B,MATCH(Consumer_Complaints!E239,State_Code_Name!C:C,0)) -> Massachusetts | L239: =H239-G239 -> 0 | M239: =YEAR(G239) -> 2016 | N239: =IF(MONTH(G239)<=3,"Q1",IF(MONTH(G239)<=6,"Q2",IF(MONTH(G239)<=9,"Q3","Q4"))) -> Q3
A240: 1441771 | B240: First Associates Loan Servicing LLC | C240: Student loan | D240: Can't repay my loan | E240: TX | F240: Web | G240: 42183 | H240: 42183 | I240: Yes | J240: No | K240: =INDEX(State_Code_Name!B:B,MATCH(Consumer_Complaints!E240,State_Code_Name!C:C,0)) -> Texas | L240: =H240-G240 -> 0 | M240: =YEAR(G240) -> 2015 | N240: =IF(MONTH(G240)<=3,"Q1",IF(MONTH(G240)<=6,"Q2",IF(MONTH(G240)<=9,"Q3","Q4"))) -> Q2
A241: 1723768 | B241: Ally Financial Inc. | C241: Consumer Loan | D241: Managing the loan or lease | E241: KY | F241: Web | G241: 42369 | H241: 42369 | I241: Yes | J241: No | K241: =INDEX(State_Code_Name!B:B,MATCH(Consumer_Complaints!E241,State_Code_Name!C:C,0)) -> Kentucky | L241: =H241-G241 -> 0 | M241: =YEAR(G241) -> 2015 | N241: =IF(MONTH(G241)<=3,"Q1",IF(MONTH(G241)<=6,"Q2",IF(MONTH(G241)<=9,"Q3","Q4"))) -> Q4
A242: 692391 | B242: TransUnion Intermediate Holdings, Inc. | C242: Credit reporting | D242: Improper use of my credit report | E242: TX | F242: Web | G242: 41669 | H242: 41669 | I242: Yes | J242: No | K242: =INDEX(State_Code_Name!B:B,MATCH(Consumer_Complaints!E242,State_Code_Name!C:C,0)) -> Texas | L242: =H242-G242 -> 0 | M242: =YEAR(G242) -> 2014 | N242: =IF(MONTH(G242)<=3,"Q1",IF(MONTH(G242)<=6,"Q2",IF(MONTH(G242)<=9,"Q3","Q4"))) -> Q1
A243: 1341628 | B243: BBVA Compass | C243: Bank account or service | D243: Deposits and withdrawals | E243: TX | F243: Email | G243: 42116 | H243: 42121 | I243: Yes | J243: No | K243: =INDEX(State_Code_Name!B:B,MATCH(Consumer_Complaints!E243,State_Code_Name!C:C,0)) -> Texas | L243: =H243-G243 -> 5 | M243: =YEAR(G243) -> 2015 | N243: =IF(MONTH(G243)<=3,"Q1",IF(MONTH(G243)<=6,"Q2",IF(MONTH(G243)<=9,"Q3","Q4"))) -> Q2
A244: 1261270 | B244: HSBC North America Holdings Inc. | C244: Bank account or service | D244: Account opening, closing, or management | E244: OH | F244: Email | G244: 42062 | H244: 42066 | I244: Yes | J244: Yes | K244: =INDEX(State_Code_Name!B:B,MATCH(Consumer_Complaints!E244,State_Code_Name!C:C,0)) -> Ohio | L244: =H244-G244 -> 4 | M244: =YEAR(G244) -> 2015 | N244: =IF(MONTH(G244)<=3,"Q1",IF(MONTH(G244)<=6,"Q2",IF(MONTH(G244)<=9,"Q3","Q4"))) -> Q1
A245: 1342464 | B245: Arbor Residential Mortgage LLC | C245: Mortgage | D245: Loan servicing, payments, escrow account | E245: OR | F245: Web | G245: 42116 | H245: 42116 | I245: Yes | J245: No | K245: =INDEX(State_Code_Name!B:B,MATCH(Consumer_Complaints!E245,State_Code_Name!C:C,0)) -> Oregon | L245: =H245-G245 -> 0 | M245: =YEAR(G245) -> 2015 | N245: =IF(MONTH(G245)<=3,"Q1",IF(MONTH(G245)<=6,"Q2",IF(MONTH(G245)<=9,"Q3","Q4"))) -> Q2
A246: 1428092 | B246: Ditech Financial LLC | C246: Mortgage | D246: Loan servicing, payments, escrow account | E246: IL | F246: Web | G246: 42173 | H246: 42173 | I246: Yes | J246: No | K246: =INDEX(State_Code_Name!B:B,MATCH(Consumer_Complaints!E246,State_Code_Name!C:C,0)) -> Illinois | L246: =H246-G246 -> 0 | M246: =YEAR(G246) -> 2015 | N246: =IF(MONTH(G246)<=3,"Q1",IF(MONTH(G246)<=6,"Q2",IF(MONTH(G246)<=9,"Q3","Q4"))) -> Q2
... A366: 505375 | B366: Wells Fargo & Company | C366: Student loan | D366: Repaying your loan | E366: OR | F366: Web | G366: 41513 | H366: 41515 | I366: Yes | J366: No | K366: =INDEX(State_Code_Name!B:B,MATCH(Consumer_Complaints!E366,State_Code_Name!C:C,0)) -> Oregon | L366: =H366-G366 -> 2 | M366: =YEAR(G366) -> 2013 | N366: =IF(MONTH(G366)<=3,"Q1",IF(MONTH(G366)<=6,"Q2",IF(MONTH(G366)<=9,"Q3","Q4"))) -> Q3
A367: 990682 | B367: JPMorgan Chase & Co. | C367: Bank account or service | D367: Account opening, closing, or management | F367: Email | G367: 41870 | H367: 41872 | I367: Yes | J367: No | K367: =INDEX(State_Code_Name!B:B,MATCH(Consumer_Complaints!E367,State_Code_Name!C:C,0)) -> #N/A | L367: =H367-G367 -> 2 | M367: =YEAR(G367) -> 2014 | N367: =IF(MONTH(G367)<=3,"Q1",IF(MONTH(G367)<=6,"Q2",IF(MONTH(G367)<=9,"Q3","Q4"))) -> Q3
A368: 577422 | B368: Experian | C368: Credit reporting | D368: Unable to get credit report/credit score | E368: AZ | F368: Web | G368: 41577 | H368: 41577 | I368: Yes | J368: No | K368: =INDEX(State_Code_Name!B:B,MATCH(Consumer_Complaints!E368,State_Code_Name!C:C,0)) -> Arizona | L368: =H368-G368 -> 0 | M368: =YEAR(G368) -> 2013 | N368: =IF(MONTH(G368)<=3,"Q1",IF(MONTH(G368)<=6,"Q2",IF(MONTH(G368)<=9,"Q3","Q4"))) -> Q4
A369: 1358394 | B369: BB&T Financial | C369: Money transfers | D369: Money was not available when promised | E369: NC | F369: Web | G369: 42099 | H369: 42099 | I369: Yes | J369: No | K369: =INDEX(State_Code_Name!B:B,MATCH(Consumer_Complaints!E369,State_Code_Name!C:C,0)) -> North Carolina | L369: =H369-G369 -> 0 | M369: =YEAR(G369) -> 2015 | N369: =IF(MONTH(G369)<=3,"Q1",IF(MONTH(G369)<=6,"Q2",IF(MONTH(G369)<=9,"Q3","Q4"))) -> Q2
A370: 1413724 | B370: JPMorgan Chase & Co. | C370: Mortgage | D370: Loan servicing, payments, escrow account | E370: CA | F370: Web | G370: 42253 | H370: 42253 | I370: Yes | J370: Yes | K370: =INDEX(State_Code_Name!B:B,MATCH(Consumer_Complaints!E370,State_Code_Name!C:C,0)) -> California | L370: =H370-G370 -> 0 | M370: =YEAR(G370) -> 2015 | N370: =IF(MONTH(G370)<=3,"Q1",IF(MONTH(G370)<=6,"Q2",IF(MONTH(G370)<=9,"Q3","Q4"))) -> Q3
A371: 1747095 | B371: Citibank | C371: Debt collection | D371: Improper contact or sharing of info | E371: CA | F371: Web | G371: 42388 | H371: 42388 | I371: Yes | J371: Yes | K371: =INDEX(State_Code_Name!B:B,MATCH(Consumer_Complaints!E371,State_Code_Name!C:C,0)) -> California | L371: =H371-G371 -> 0 | M371: =YEAR(G371) -> 2016 | N371: =IF(MONTH(G371)<=3,"Q1",IF(MONTH(G371)<=6,"Q2",IF(MONTH(G371)<=9,"Q3","Q4"))) -> Q1
A372: 2092172 | B372: Union Bank | C372: Bank account or service | D372: Account opening, closing, or management | E372: CA | F372: Web | G372: 42378 | H372: 42378 | I372: Yes | J372: Yes | K372: =INDEX(State_Code_Name!B:B,MATCH(Consumer_Complaints!E372,State_Code_Name!C:C,0)) -> California | L372: =H372-G372 -> 0 | M372: =YEAR(G372) -> 2016 | N372: =IF(MONTH(G372)<=3,"Q1",IF(MONTH(G372)<=6,"Q2",IF(MONTH(G372)<=9,"Q3","Q4"))) -> Q1
A373: 2064507 | B373: Santander Consumer USA Holdings Inc | C373: Consumer Loan | D373: Taking out the loan or lease | E373: NY | F373: Fax | G373: 42597 | H373: 42599 | I373: Yes | J373: No | K373: =INDEX(State_Code_Name!B:B,MATCH(Consumer_Complaints!E373,State_Code_Name!C:C,0)) -> New York | L373: =H373-G373 -> 2 | M373: =YEAR(G373) -> 2016 | N373: =IF(MONTH(G373)<=3,"Q1",IF(MONTH(G373)<=6,"Q2",IF(MONTH(G373)<=9,"Q3","Q4"))) -> Q3
A374: 1535164 | B374: Equifax | C374: Credit reporting | D374: Unable to get credit report/credit score | E374: OR | F374: Web | G374: 42241 | H374: 42241 | I374: Yes | J374: No | K374: =INDEX(State_Code_Name!B:B,MATCH(Consumer_Complaints!E374,State_Code_Name!C:C,0)) -> Oregon | L374: =H374-G374 -> 0 | M374: =YEAR(G374) -> 2015 | N374: =IF(MONTH(G374)<=3,"Q1",IF(MONTH(G374)<=6,"Q2",IF(MONTH(G374)<=9,"Q3","Q4"))) -> Q3
A375: 1582476 | B375: Resurgent Capital Services L.P. | C375: Debt collection | D375: Loan modification,collection,foreclosure | E375: FL | F375: Web | G375: 42275 | H375: 42275 | I375: Yes | J375: No | K375: =INDEX(State_Code_Name!B:B,MATCH(Consumer_Complaints!E375,State_Code_Name!C:C,0)) -> Florida | L375: =H375-G375 -> 0 | M375: =YEAR(G375) -> 2015 | N375: =IF(MONTH(G375)<=3,"Q1",IF(MONTH(G375)<=6,"Q2",IF(MONTH(G375)<=9,"Q3","Q4"))) -> Q3
A376: 2019176 | B376: I.C. System, Inc. | C376: Debt collection | D376: False statements or representation | E376: GA | F376: Web | G376: 42570 | H376: 42570 | I376: Yes | J376: No | K376: =INDEX(State_Code_Name!B:B,MATCH(Consumer_Complaints!E376,State_Code_Name!C:C,0)) -> Georgia | L376: =H376-G376 -> 0 | M376: =YEAR(G376) -> 2016 | N376: =IF(MONTH(G376)<=3,"Q1",IF(MONTH(G376)<=6,"Q2",IF(MONTH(G376)<=9,"Q3","Q4"))) -> Q3
A377: 1609950 | B377: Experian | C377: Credit reporting | D377: Unable to get credit report/credit score | E377: VA | F377: Email | G377: 42293 | H377: 42293 | I377: Yes | J377: No | K377: =INDEX(State_Code_Name!B:B,MATCH(Consumer_Complaints!E377,State_Code_Name!C:C,0)) -> Virginia | L377: =H377-G377 -> 0 | M377: =YEAR(G377) -> 2015 | N377: =IF(MONTH(G377)<=3,"Q1",IF(MONTH(G377)<=6,"Q2",IF(MONTH(G377)<=9,"Q3","Q4"))) -> Q4
A378: 1604883 | B378: Delbert Services | C378: Consumer Loan | D378: Shopping for a line of credit | E378: SC | F378: Web | G378: 42290 | H378: 42290 | I378: Yes | J378: No | K378: =INDEX(State_Code_Name!B:B,MATCH(Consumer_Complaints!E378,State_Code_Name!C:C,0)) -> South Carolina | L378: =H378-G378 -> 0 | M378: =YEAR(G378) -> 2015 | N378: =IF(MONTH(G378)<=3,"Q1",IF(MONTH(G378)<=6,"Q2",IF(MONTH(G378)<=9,"Q3","Q4"))) -> Q4
A379: 1305386 | B379: CIT Bank National Association | C379: Mortgage | D379: Application, originator, mortgage broker | E379: NV | F379: Web | G379: 42090 | H379: 42090 | I379: Yes | J379: No | K379: =INDEX(State_Code_Name!B:B,MATCH(Consumer_Complaints!E379,State_Code_Name!C:C,0)) -> Nevada | L379: =H379-G379 -> 0 | M379: =YEAR(G379) -> 2015 | N379: =IF(MONTH(G379)<=3,"Q1",IF(MONTH(G379)<=6,"Q2",IF(MONTH(G379)<=9,"Q3","Q4"))) -> Q1
... A400: 1553762 | B400: Seterus, Inc. | C400: Mortgage | D400: Loan servicing, payments, escrow account | E400: CA | F400: Web | G400: 42133 | H400: 42133 | I400: Yes | J400: No | K400: =INDEX(State_Code_Name!B:B,MATCH(Consumer_Complaints!E400,State_Code_Name!C:C,0)) -> California | L400: =H400-G400 -> 0 | M400: =YEAR(G400) -> 2015 | N400: =IF(MONTH(G400)<=3,"Q1",IF(MONTH(G400)<=6,"Q2",IF(MONTH(G400)<=9,"Q3","Q4"))) -> Q2
A401: 1129160 | B401: Central Portfolio Control Inc. | C401: Debt collection | D401: Communication tactics | F401: Phone | G401: 41967 | H401: 41968 | I401: Yes | J401: No | K401: =INDEX(State_Code_Name!B:B,MATCH(Consumer_Complaints!E401,State_Code_Name!C:C,0)) -> #N/A | L401: =H401-G401 -> 1 | M401: =YEAR(G401) -> 2014 | N401: =IF(MONTH(G401)<=3,"Q1",IF(MONTH(G401)<=6,"Q2",IF(MONTH(G401)<=9,"Q3","Q4"))) -> Q4
A402: 1676431 | B402: Synchrony Financial | C402: Credit card | D402: Billing disputes | E402: NY | F402: Web | G402: 42338 | H402: 42338 | I402: Yes | J402: No | K402: =INDEX(State_Code_Name!B:B,MATCH(Consumer_Complaints!E402,State_Code_Name!C:C,0)) -> New York | L402: =H402-G402 -> 0 | M402: =YEAR(G402) -> 2015 | N402: =IF(MONTH(G402)<=3,"Q1",IF(MONTH(G402)<=6,"Q2",IF(MONTH(G402)<=9,"Q3","Q4"))) -> Q4
A403: 619974 | B403: Citibank | C403: Credit card | D403: Credit determination | E403: NY | F403: Postal mail | G403: 41345 | H403: 41345 | I403: Yes | J403: No | K403: =INDEX(State_Code_Name!B:B,MATCH(Consumer_Complaints!E403,State_Code_Name!C:C,0)) -> New York | L403: =H403-G403 -> 0 | M403: =YEAR(G403) -> 2013 | N403: =IF(MONTH(G403)<=3,"Q1",IF(MONTH(G403)<=6,"Q2",IF(MONTH(G403)<=9,"Q3","Q4"))) -> Q1
A404: 1880668 | B404: TransUnion Intermediate Holdings, Inc. | C404: Credit reporting | D404: Credit monitoring or identity protection | E404: NV | F404: Web | G404: 42475 | H404: 42475 | I404: Yes | J404: No | K404: =INDEX(State_Code_Name!B:B,MATCH(Consumer_Complaints!E404,State_Code_Name!C:C,0)) -> Nevada | L404: =H404-G404 -> 0 | M404: =YEAR(G404) -> 2016 | N404: =IF(MONTH(G404)<=3,"Q1",IF(MONTH(G404)<=6,"Q2",IF(MONTH(G404)<=9,"Q3","Q4"))) -> Q2
A405: 1791764 | B405: Loan Care | C405: Mortgage | D405: Loan servicing, payments, escrow account | E405: TX | F405: Web | G405: 42417 | H405: 42417 | I405: Yes | J405: No | K405: =INDEX(State_Code_Name!B:B,MATCH(Consumer_Complaints!E405,State_Code_Name!C:C,0)) -> Texas | L405: =H405-G405 -> 0 | M405: =YEAR(G405) -> 2016 | N405: =IF(MONTH(G405)<=3,"Q1",IF(MONTH(G405)<=6,"Q2",IF(MONTH(G405)<=9,"Q3","Q4"))) -> Q1
A406: 229572 | B406: Experian | C406: Credit reporting | D406: Credit reporting company's investigation | E406: CA | F406: Web | G406: 41609 | H406: 41609 | I406: Yes | J406: Yes | K406: =INDEX(State_Code_Name!B:B,MATCH(Consumer_Complaints!E406,State_Code_Name!C:C,0)) -> California | L406: =H406-G406 -> 0 | M406: =YEAR(G406) -> 2013 | N406: =IF(MONTH(G406)<=3,"Q1",IF(MONTH(G406)<=6,"Q2",IF(MONTH(G406)<=9,"Q3","Q4"))) -> Q4
A407: 1332700 | B407: Fifth Third Financial Corporation | C407: Credit card | D407: Rewards | E407: OH | F407: Web | G407: 42110 | H407: 42110 | I407: Yes | J407: Yes | K407: =INDEX(State_Code_Name!B:B,MATCH(Consumer_Complaints!E407,State_Code_Name!C:C,0)) -> Ohio | L407: =H407-G407 -> 0 | M407: =YEAR(G407) -> 2015 | N407: =IF(MONTH(G407)<=3,"Q1",IF(MONTH(G407)<=6,"Q2",IF(MONTH(G407)<=9,"Q3","Q4"))) -> Q2
A408: 931046 | B408: Experian | C408: Credit reporting | D408: Credit monitoring or identity protection | E408: SC | F408: Web | G408: 41919 | H408: 41919 | I408: Yes | J408: No | K408: =INDEX(State_Code_Name!B:B,MATCH(Consumer_Complaints!E408,State_Code_Name!C:C,0)) -> South Carolina | L408: =H408-G408 -> 0 | M408: =YEAR(G408) -> 2014 | N408: =IF(MONTH(G408)<=3,"Q1",IF(MONTH(G408)<=6,"Q2",IF(MONTH(G408)<=9,"Q3","Q4"))) -> Q4
A409: 258939 | B409: JPMorgan Chase & Co. | C409: Consumer Loan | D409: Taking out the loan or lease | E409: WV | F409: Web | G409: 41298 | H409: 41298 | I409: Yes | J409: No | K409: =INDEX(State_Code_Name!B:B,MATCH(Consumer_Complaints!E409,State_Code_Name!C:C,0)) -> West Virginia | L409: =H409-G409 -> 0 | M409: =YEAR(G409) -> 2013 | N409: =IF(MONTH(G409)<=3,"Q1",IF(MONTH(G409)<=6,"Q2",IF(MONTH(G409)<=9,"Q3","Q4"))) -> Q1
A410: 1452746 | B410: Discover | C410: Credit card | D410: Closing/Cancelling account | E410: AZ | F410: Web | G410: 42162 | H410: 42162 | I410: Yes | J410: No | K410: =INDEX(State_Code_Name!B:B,MATCH(Consumer_Complaints!E410,State_Code_Name!C:C,0)) -> Arizona | L410: =H410-G410 -> 0 | M410: =YEAR(G410) -> 2015 | N410: =IF(MONTH(G410)<=3,"Q1",IF(MONTH(G410)<=6,"Q2",IF(MONTH(G410)<=9,"Q3","Q4"))) -> Q2
A411: 385179 | B411: TransUnion Intermediate Holdings, Inc. | C411: Credit reporting | D411: Unable to get credit report/credit score | E411: MN | F411: Postal mail | G411: 41381 | H411: 41382 | I411: Yes | J411: No | K411: =INDEX(State_Code_Name!B:B,MATCH(Consumer_Complaints!E411,State_Code_Name!C:C,0)) -> Minnesota | L411: =H411-G411 -> 1 | M411: =YEAR(G411) -> 2013 | N411: =IF(MONTH(G411)<=3,"Q1",IF(MONTH(G411)<=6,"Q2",IF(MONTH(G411)<=9,"Q3","Q4"))) -> Q2
A412: 1509816 | B412: TransUnion Intermediate Holdings, Inc. | C412: Credit reporting | D412: Improper use of my credit report | E412: CA | F412: Web | G412: 42224 | H412: 42285 | I412: Yes | J412: No | K412: =INDEX(State_Code_Name!B:B,MATCH(Consumer_Complaints!E412,State_Code_Name!C:C,0)) -> California | L412: =H412-G412 -> 61 | M412: =YEAR(G412) -> 2015 | N412: =IF(MONTH(G412)<=3,"Q1",IF(MONTH(G412)<=6,"Q2",IF(MONTH(G412)<=9,"Q3","Q4"))) -> Q3
A413: 2084625 | B413: Experian | C413: Credit reporting | D413: Unable to get credit report/credit score | E413: WI | F413: Web | G413: 42610 | H413: 42613 | I413: Yes | J413: No | K413: =INDEX(State_Code_Name!B:B,MATCH(Consumer_Complaints!E413,State_Code_Name!C:C,0)) -> Wisconsin | L413: =H413-G413 -> 3 | M413: =YEAR(G413) -> 2016 | N413: =IF(MONTH(G413)<=3,"Q1",IF(MONTH(G413)<=6,"Q2",IF(MONTH(G413)<=9,"Q3","Q4"))) -> Q3
... A438: 1298250 | B438: Capital One | C438: Bank account or service | D438: Deposits and withdrawals | E438: NY | F438: Phone | G438: 42087 | H438: 42088 | I438: Yes | J438: No | K438: =INDEX(State_Code_Name!B:B,MATCH(Consumer_Complaints!E438,State_Code_Name!C:C,0)) -> New York | L438: =H438-G438 -> 1 | M438: =YEAR(G438) -> 2015 | N438: =IF(MONTH(G438)<=3,"Q1",IF(MONTH(G438)<=6,"Q2",IF(MONTH(G438)<=9,"Q3","Q4"))) -> Q1
A439: 1648406 | B439: Bank of Hawaii | C439: Bank account or service | D439: Deposits and withdrawals | F439: Email | G439: 42288 | H439: 42335 | I439: Yes | J439: No | K439: =INDEX(State_Code_Name!B:B,MATCH(Consumer_Complaints!E439,State_Code_Name!C:C,0)) -> #N/A | L439: =H439-G439 -> 47 | M439: =YEAR(G439) -> 2015 | N439: =IF(MONTH(G439)<=3,"Q1",IF(MONTH(G439)<=6,"Q2",IF(MONTH(G439)<=9,"Q3","Q4"))) -> Q4
A440: 2091606 | B440: Citibank | C440: Credit card | D440: Payoff process | E440: NY | F440: Web | G440: 42378 | H440: 42378 | I440: Yes | J440: Yes | K440: =INDEX(State_Code_Name!B:B,MATCH(Consumer_Complaints!E440,State_Code_Name!C:C,0)) -> New York | L440: =H440-G440 -> 0 | M440: =YEAR(G440) -> 2016 | N440: =IF(MONTH(G440)<=3,"Q1",IF(MONTH(G440)<=6,"Q2",IF(MONTH(G440)<=9,"Q3","Q4"))) -> Q1
A441: 1572393 | B441: Wells Fargo & Company | C441: Mortgage | D441: Credit decision / Underwriting | E441: LA | F441: Web | G441: 42268 | H441: 42268 | I441: Yes | J441: No | K441: =INDEX(State_Code_Name!B:B,MATCH(Consumer_Complaints!E441,State_Code_Name!C:C,0)) -> Louisiana | L441: =H441-G441 -> 0 | M441: =YEAR(G441) -> 2015 | N441: =IF(MONTH(G441)<=3,"Q1",IF(MONTH(G441)<=6,"Q2",IF(MONTH(G441)<=9,"Q3","Q4"))) -> Q3
A442: 559485 | B442: Wells Fargo & Company | C442: Mortgage | D442: Loan servicing, payments, escrow account | E442: PA | F442: Web | G442: 41562 | H442: 41565 | I442: Yes | J442: Yes | K442: =INDEX(State_Code_Name!B:B,MATCH(Consumer_Complaints!E442,State_Code_Name!C:C,0)) -> Pennsylvania | L442: =H442-G442 -> 3 | M442: =YEAR(G442) -> 2013 | N442: =IF(MONTH(G442)<=3,"Q1",IF(MONTH(G442)<=6,"Q2",IF(MONTH(G442)<=9,"Q3","Q4"))) -> Q4
A443: 361753 | B443: Wells Fargo & Company | C443: Bank account or service | D443: Account opening, closing, or management | E443: NJ | F443: Email | G443: 41354 | H443: 41358 | I443: Yes | J443: Yes | K443: =INDEX(State_Code_Name!B:B,MATCH(Consumer_Complaints!E443,State_Code_Name!C:C,0)) -> New Jersey | L443: =H443-G443 -> 4 | M443: =YEAR(G443) -> 2013 | N443: =IF(MONTH(G443)<=3,"Q1",IF(MONTH(G443)<=6,"Q2",IF(MONTH(G443)<=9,"Q3","Q4"))) -> Q1
A444: 1072715 | B444: Equifax | C444: Credit reporting | D444: Unable to get credit report/credit score | E444: MA | F444: Web | G444: 41927 | H444: 41927 | I444: Yes | J444: Yes | K444: =INDEX(State_Code_Name!B:B,MATCH(Consumer_Complaints!E444,State_Code_Name!C:C,0)) -> Massachusetts | L444: =H444-G444 -> 0 | M444: =YEAR(G444) -> 2014 | N444: =IF(MONTH(G444)<=3,"Q1",IF(MONTH(G444)<=6,"Q2",IF(MONTH(G444)<=9,"Q3","Q4"))) -> Q4
A445: 2025015 | B445: Citibank | C445: Credit card | D445: Late fee | E445: IL | F445: Email | G445: 42573 | H445: 42576 | I445: Yes | J445: Yes | K445: =INDEX(State_Code_Name!B:B,MATCH(Consumer_Complaints!E445,State_Code_Name!C:C,0)) -> Illinois | L445: =H445-G445 -> 3 | M445: =YEAR(G445) -> 2016 | N445: =IF(MONTH(G445)<=3,"Q1",IF(MONTH(G445)<=6,"Q2",IF(MONTH(G445)<=9,"Q3","Q4"))) -> Q3
A446: 1354267 | B446: Navient Solutions, Inc. | C446: Debt collection | D446: False statements or representation | E446: IL | F446: Web | G446: 42124 | H446: 42124 | I446: Yes | J446: No | K446: =INDEX(State_Code_Name!B:B,MATCH(Consumer_Complaints!E446,State_Code_Name!C:C,0)) -> Illinois | L446: =H446-G446 -> 0 | M446: =YEAR(G446) -> 2015 | N446: =IF(MONTH(G446)<=3,"Q1",IF(MONTH(G446)<=6,"Q2",IF(MONTH(G446)<=9,"Q3","Q4"))) -> Q2
A447: 2024363 | B447: CoreLogic | C447: Credit reporting | D447: Improper use of my credit report | E447: LA | F447: Postal mail | G447: 42572 | H447: 42573 | I447: Yes | J447: No | K447: =INDEX(State_Code_Name!B:B,MATCH(Consumer_Complaints!E447,State_Code_Name!C:C,0)) -> Louisiana | L447: =H447-G447 -> 1 | M447: =YEAR(G447) -> 2016 | N447: =IF(MONTH(G447)<=3,"Q1",IF(MONTH(G447)<=6,"Q2",IF(MONTH(G447)<=9,"Q3","Q4"))) -> Q3
A448: 1844588 | B448: Citibank | C448: Mortgage | D448: Loan servicing, payments, escrow account | E448: MA | F448: Phone | G448: 42451 | H448: 42451 | I448: Yes | J448: No | K448: =INDEX(State_Code_Name!B:B,MATCH(Consumer_Complaints!E448,State_Code_Name!C:C,0)) -> Massachusetts | L448: =H448-G448 -> 0 | M448: =YEAR(G448) -> 2016 | N448: =IF(MONTH(G448)<=3,"Q1",IF(MONTH(G448)<=6,"Q2",IF(MONTH(G448)<=9,"Q3","Q4"))) -> Q1
A449: 1837443 | B449: Discover | C449: Debt collection | D449: Loan modification,collection,foreclosure | E449: MN | F449: Email | G449: 42446 | H449: 42447 | I449: Yes | J449: No | K449: =INDEX(State_Code_Name!B:B,MATCH(Consumer_Complaints!E449,State_Code_Name!C:C,0)) -> Minnesota | L449: =H449-G449 -> 1 | M449: =YEAR(G449) -> 2016 | N449: =IF(MONTH(G449)<=3,"Q1",IF(MONTH(G449)<=6,"Q2",IF(MONTH(G449)<=9,"Q3","Q4"))) -> Q1
A450: 1866698 | B450: Ditech Financial LLC | C450: Mortgage | D450: Loan servicing, payments, escrow account | E450: PA | F450: Web | G450: 42525 | H450: 42525 | I450: Yes | J450: No | K450: =INDEX(State_Code_Name!B:B,MATCH(Consumer_Complaints!E450,State_Code_Name!C:C,0)) -> Pennsylvania | L450: =H450-G450 -> 0 | M450: =YEAR(G450) -> 2016 | N450: =IF(MONTH(G450)<=3,"Q1",IF(MONTH(G450)<=6,"Q2",IF(MONTH(G450)<=9,"Q3","Q4"))) -> Q2
A451: 1630877 | B451: Empowerment Ventures, LLC | C451: Prepaid card | D451: Managing, opening, or closing account | E451: MI | F451: Web | G451: 42306 | H451: 42321 | I451: Yes | J451: No | K451: =INDEX(State_Code_Name!B:B,MATCH(Consumer_Complaints!E451,State_Code_Name!C:C,0)) -> Michigan | L451: =H451-G451 -> 15 | M451: =YEAR(G451) -> 2015 | N451: =IF(MONTH(G451)<=3,"Q1",IF(MONTH(G451)<=6,"Q2",IF(MONTH(G451)<=9,"Q3","Q4"))) -> Q4
... A546: 1874763 | B546: Commonwealth Financial Systems, Inc. | C546: Debt collection | D546: Loan modification,collection,foreclosure | E546: TX | F546: Web | G546: 42708 | H546: 42708 | I546: Yes | J546: No | K546: =INDEX(State_Code_Name!B:B,MATCH(Consumer_Complaints!E546,State_Code_Name!C:C,0)) -> Texas | L546: =H546-G546 -> 0 | M546: =YEAR(G546) -> 2016 | N546: =IF(MONTH(G546)<=3,"Q1",IF(MONTH(G546)<=6,"Q2",IF(MONTH(G546)<=9,"Q3","Q4"))) -> Q4
A547: 1853841 | B547: SquareTwo Financial Corporation | C547: Debt collection | D547: False statements or representation | F547: Web | G547: 42458 | H547: 42458 | I547: Yes | J547: No | K547: =INDEX(State_Code_Name!B:B,MATCH(Consumer_Complaints!E547,State_Code_Name!C:C,0)) -> #N/A | L547: =H547-G547 -> 0 | M547: =YEAR(G547) -> 2016 | N547: =IF(MONTH(G547)<=3,"Q1",IF(MONTH(G547)<=6,"Q2",IF(MONTH(G547)<=9,"Q3","Q4"))) -> Q1
A548: 726229 | B548: Check into Cash, Inc. | C548: Debt collection | D548: Communication tactics | E548: CA | F548: Phone | G548: 41691 | H548: 41694 | I548: Yes | J548: No | K548: =INDEX(State_Code_Name!B:B,MATCH(Consumer_Complaints!E548,State_Code_Name!C:C,0)) -> California | L548: =H548-G548 -> 3 | M548: =YEAR(G548) -> 2014 | N548: =IF(MONTH(G548)<=3,"Q1",IF(MONTH(G548)<=6,"Q2",IF(MONTH(G548)<=9,"Q3","Q4"))) -> Q1
A549: 2005158 | B549: JPMorgan Chase & Co. | C549: Bank account or service | D549: Problems caused by my funds being low | E549: IL | F549: Web | G549: 42620 | H549: 42620 | I549: Yes | J549: No | K549: =INDEX(State_Code_Name!B:B,MATCH(Consumer_Complaints!E549,State_Code_Name!C:C,0)) -> Illinois | L549: =H549-G549 -> 0 | M549: =YEAR(G549) -> 2016 | N549: =IF(MONTH(G549)<=3,"Q1",IF(MONTH(G549)<=6,"Q2",IF(MONTH(G549)<=9,"Q3","Q4"))) -> Q3
A550: 636688 | B550: Valley National Bank | C550: Bank account or service | D550: Problems caused by my funds being low | E550: NY | F550: Email | G550: 41625 | H550: 41628 | I550: Yes | J550: No | K550: =INDEX(State_Code_Name!B:B,MATCH(Consumer_Complaints!E550,State_Code_Name!C:C,0)) -> New York | L550: =H550-G550 -> 3 | M550: =YEAR(G550) -> 2013 | N550: =IF(MONTH(G550)<=3,"Q1",IF(MONTH(G550)<=6,"Q2",IF(MONTH(G550)<=9,"Q3","Q4"))) -> Q4
A551: 2044495 | B551: The Huntington National Bank | C551: Bank account or service | D551: Account opening, closing, or management | E551: OH | F551: Web | G551: 42437 | H551: 42437 | I551: Yes | J551: No | K551: =INDEX(State_Code_Name!B:B,MATCH(Consumer_Complaints!E551,State_Code_Name!C:C,0)) -> Ohio | L551: =H551-G551 -> 0 | M551: =YEAR(G551) -> 2016 | N551: =IF(MONTH(G551)<=3,"Q1",IF(MONTH(G551)<=6,"Q2",IF(MONTH(G551)<=9,"Q3","Q4"))) -> Q1
A552: 2164077 | B552: Citizens Financial Group, Inc. | C552: Bank account or service | D552: Making/receiving payments, sending money | E552: MI | F552: Web | G552: 42660 | H552: 42660 | I552: Yes | J552: Yes | K552: =INDEX(State_Code_Name!B:B,MATCH(Consumer_Complaints!E552,State_Code_Name!C:C,0)) -> Michigan | L552: =H552-G552 -> 0 | M552: =YEAR(G552) -> 2016 | N552: =IF(MONTH(G552)<=3,"Q1",IF(MONTH(G552)<=6,"Q2",IF(MONTH(G552)<=9,"Q3","Q4"))) -> Q4
A553: 1058876 | B553: HSBC North America Holdings Inc. | C553: Mortgage | D553: Application, originator, mortgage broker | E553: NY | F553: Web | G553: 41800 | H553: 41800 | I553: Yes | J553: Yes | K553: =INDEX(State_Code_Name!B:B,MATCH(Consumer_Complaints!E553,State_Code_Name!C:C,0)) -> New York | L553: =H553-G553 -> 0 | M553: =YEAR(G553) -> 2014 | N553: =IF(MONTH(G553)<=3,"Q1",IF(MONTH(G553)<=6,"Q2",IF(MONTH(G553)<=9,"Q3","Q4"))) -> Q2
A554: 1677812 | B554: Northland Group, Inc. | C554: Debt collection | D554: Communication tactics | E554: OH | F554: Web | G554: 42016 | H554: 42016 | I554: Yes | J554: No | K554: =INDEX(State_Code_Name!B:B,MATCH(Consumer_Complaints!E554,State_Code_Name!C:C,0)) -> Ohio | L554: =H554-G554 -> 0 | M554: =YEAR(G554) -> 2015 | N554: =IF(MONTH(G554)<=3,"Q1",IF(MONTH(G554)<=6,"Q2",IF(MONTH(G554)<=9,"Q3","Q4"))) -> Q1
A555: 1339584 | B555: NetSpend Corporation, a TSYS Company | C555: Prepaid card | D555: Adding money | E555: NC | F555: Web | G555: 42115 | H555: 42118 | I555: Yes | J555: No | K555: =INDEX(State_Code_Name!B:B,MATCH(Consumer_Complaints!E555,State_Code_Name!C:C,0)) -> North Carolina | L555: =H555-G555 -> 3 | M555: =YEAR(G555) -> 2015 | N555: =IF(MONTH(G555)<=3,"Q1",IF(MONTH(G555)<=6,"Q2",IF(MONTH(G555)<=9,"Q3","Q4"))) -> Q2
A556: 1833492 | B556: MoneyGram | C556: Money transfers | D556: Money was not available when promised | E556: CA | F556: Postal mail | G556: 42444 | H556: 42454 | I556: Yes | J556: No | K556: =INDEX(State_Code_Name!B:B,MATCH(Consumer_Complaints!E556,State_Code_Name!C:C,0)) -> California | L556: =H556-G556 -> 10 | M556: =YEAR(G556) -> 2016 | N556: =IF(MONTH(G556)<=3,"Q1",IF(MONTH(G556)<=6,"Q2",IF(MONTH(G556)<=9,"Q3","Q4"))) -> Q1
A557: 472813 | B557: Navient Solutions, Inc. | C557: Student loan | D557: Repaying your loan | E557: NY | F557: Web | G557: 41313 | H557: 41402 | I557: Yes | J557: Yes | K557: =INDEX(State_Code_Name!B:B,MATCH(Consumer_Complaints!E557,State_Code_Name!C:C,0)) -> New York | L557: =H557-G557 -> 89 | M557: =YEAR(G557) -> 2013 | N557: =IF(MONTH(G557)<=3,"Q1",IF(MONTH(G557)<=6,"Q2",IF(MONTH(G557)<=9,"Q3","Q4"))) -> Q1
A558: 1114757 | B558: Santander Bank US | C558: Mortgage | D558: Loan servicing, payments, escrow account | E558: NJ | F558: Email | G558: 41956 | H558: 41962 | I558: Yes | J558: No | K558: =INDEX(State_Code_Name!B:B,MATCH(Consumer_Complaints!E558,State_Code_Name!C:C,0)) -> New Jersey | L558: =H558-G558 -> 6 | M558: =YEAR(G558) -> 2014 | N558: =IF(MONTH(G558)<=3,"Q1",IF(MONTH(G558)<=6,"Q2",IF(MONTH(G558)<=9,"Q3","Q4"))) -> Q4
A559: 1303948 | B559: Ditech Financial LLC | C559: Debt collection | D559: Communication tactics | E559: TX | F559: Web | G559: 42090 | H559: 42090 | I559: Yes | J559: No | K559: =INDEX(State_Code_Name!B:B,MATCH(Consumer_Complaints!E559,State_Code_Name!C:C,0)) -> Texas | L559: =H559-G559 -> 0 | M559: =YEAR(G559) -> 2015 | N559: =IF(MONTH(G559)<=3,"Q1",IF(MONTH(G559)<=6,"Q2",IF(MONTH(G559)<=9,"Q3","Q4"))) -> Q1
... A680: 1809721 | B680: Carrington Mortgage Holdings, LLC. | C680: Mortgage | D680: Loan servicing, payments, escrow account | E680: IL | F680: Web | G680: 42372 | H680: 42372 | I680: Yes | J680: No | K680: =INDEX(State_Code_Name!B:B,MATCH(Consumer_Complaints!E680,State_Code_Name!C:C,0)) -> Illinois | L680: =H680-G680 -> 0 | M680: =YEAR(G680) -> 2016 | N680: =IF(MONTH(G680)<=3,"Q1",IF(MONTH(G680)<=6,"Q2",IF(MONTH(G680)<=9,"Q3","Q4"))) -> Q1
A681: 414274 | B681: Wells Fargo & Company | C681: Mortgage | D681: Loan servicing, payments, escrow account | F681: Fax | G681: 41416 | H681: 41418 | I681: Yes | J681: No | K681: =INDEX(State_Code_Name!B:B,MATCH(Consumer_Complaints!E681,State_Code_Name!C:C,0)) -> #N/A | L681: =H681-G681 -> 2 | M681: =YEAR(G681) -> 2013 | N681: =IF(MONTH(G681)<=3,"Q1",IF(MONTH(G681)<=6,"Q2",IF(MONTH(G681)<=9,"Q3","Q4"))) -> Q2
A682: 2022255 | B682: American Honda Finance Corporation | C682: Consumer Loan | D682: Managing the loan or lease | E682: NJ | F682: Web | G682: 42571 | H682: 42571 | I682: Yes | J682: No | K682: =INDEX(State_Code_Name!B:B,MATCH(Consumer_Complaints!E682,State_Code_Name!C:C,0)) -> New Jersey | L682: =H682-G682 -> 0 | M682: =YEAR(G682) -> 2016 | N682: =IF(MONTH(G682)<=3,"Q1",IF(MONTH(G682)<=6,"Q2",IF(MONTH(G682)<=9,"Q3","Q4"))) -> Q3
...

Sheet State_Code_Name
A1: Src | B1: STATE | C1: CODE | E1: Note: Data extracted using Flash fill
A2: { "STATE": "Alabama", "CODE": "AL"} | B2: Alabama | C2: AL
A3: { "STATE": "Alaska", "CODE": "AK"} | B3: Alaska | C3: AK
A4: { "STATE": "Arizona", "CODE": "AZ"} | B4: Arizona | C4: AZ
A5: { "STATE": "Arkansas", "CODE": "AR"} | B5: Arkansas | C5: AR
A6: { "STATE": "California", "CODE": "CA"} | B6: California | C6: CA
A7: { "STATE": "Colorado", "CODE": "CO"} | B7: Colorado | C7: CO
A8: { "STATE": "Connecticut", "CODE": "CT"} | B8: Connecticut | C8: CT
A9: { "STATE": "Delaware", "CODE": "DE"} | B9: Delaware | C9: DE
A10: { "STATE": "District of Columbia", "CODE": "DC"} | B10: District of Columbia | C10: DC
A11: { "STATE": "Florida", "CODE": "FL"} | B11: Florida | C11: FL
A12: { "STATE": "Georgia", "CODE": "GA"} | B12: Georgia | C12: GA
A13: { "STATE": "Hawaii", "CODE": "HI"} | B13: Hawaii | C13: HI
... A52: { "STATE": "Wyoming", "CODE": "WY"} | B52: Wyoming | C52: WY

Sheet Task 1
B3: Task 1: Working on data and combining the datasets
B4: Data in the worksheet State_Code_Name is take from internet and is available in JSON format. Perform the following tasks as part of data preparation
B5: 1. Create two new columns in the State_Code_Name worksheet and name them as STATE and CODE respectively.
B6: 2. From the JSON format, get the data (STATE and CODE) in tabular form using excel options / excel functions.
B7: 3. Create a new column in the worksheet Consumer_Complaints and name it State_Name
B8: 4. Fill the column State_name in the worksheet Consumer_Complaints with the data from the State_Code_Name worksheet
B10: Data Analysis:
B11: 5. What is the count of records for which the State Name values didn't showed up (records with #N/A) ?
B12: 6. Create a summary table to display number of complaints for only those State_Codes where State_Name is not mapped to State_Code in the worksheet Consumer_Complaints
B13: 7. Give your inferences for the possible reasons of non availabilty of the State_Name using the above steps.
B17: Note:
B18: Add a new worksheet and name it Report_Task1 to create the above report and share your inference.

Sheet Report_Task1
A1: 5. What is the count of records for which the State Name values didn't showed up (records with #N/A) ?
A2: =COUNTIF(Consumer_Complaints!K:K,"#N/A") -> 157
A4: 6. Create a summary table to display number of complaints for only those State_Codes where State_Name is not mapped to State_Code in the worksheet Consumer_Complaints
A5: State_Name | B5: #N/A
A7: Row Labels | B7: Count of Complaint ID
A8: AA | B8: 1
A9: AE | B9: 5
A10: AP | B10: 4
A11: AS | B11: 1
A12: GU | B12: 1
A13: MP | B13: 1
A14: PR | B14: 26
A15: VI | B15: 8
A16: (blank) | B16: 110
A17: Grand Total | B17: 157
A19: 7. Give your inferences for the possible reasons of non availabilty of the State_Name using the above steps.
A20: Some of the State Code entered in Comsumer complaints data are incorrect and some complaints do not have any state mapped against them.

Sheet Task 2
B3: Task 2: Working on dates
B4: 1. What is the resolution time (in days) after which the issue/complaint is resolved by the company?
B5: 2. Create a new column YEAR using the date when complaint was received.
B6: 3. Create a new column QTR (US FY) using the date when complaint was received. Column should have the quarter data based on US FY i.e. Q1 - JAN, FEB and MAR
B9: Notes:
B10: 1. The dates are not stored as proper dates. In order to perform any operation on the dates, first you have to get the date columns as date.
B11: 2. Read the dates as mm/dd/yyyy or dd-mm-yyyy
B12: 3. Perform the data cleaning step (to have proper dates) in the Consumer_Complaints worksheet

Sheet Task 3
B3: Task 3: Reporting - Create a report with following details for each Company Name ( Summarize the data at Company level )
B4: 1. Company wise total number of complaints. Sort the data in desc order of number of complaints
B5: 2. What is the number and %age of complaints where the timely response was not shared?
B6: 3. How many complaints were disputed. Also display the %age of number of complaints of the total complaints for each company.
B7: 4. Average delay in days for closure of the complaints.
B9: Notes:
B10: 1. Add a new worksheet and name it Report_Task3 to create the above report and share your inference.
B11: 2. Raw data is available at the Complaint level (one record per complaint); the report should be created at the Company level (one record per company)

Sheet Report_Task3
A1: Company | B1: Number of Complaints | C1: Number of Complaints with No timely response | D1: % of Complaints with No timely response | E1: Number of Complaints Disputed | F1: % of Complaints Disputed | G1: Average Delay (Days)
A2: Bank of America | B2: =COUNTIF(Consumer_Complaints!A:B,Report_Task3!A2) -> 1066 | C2: =COUNTIFS(Consumer_Complaints!B:B,Report_Task3!A2,Consumer_Complaints!I:I,"No") -> 5 | D2: =C2/B2 -> 0.0046904315 | E2: =COUNTIFS(Consumer_Complaints!B:B,Report_Task3!A2,Consumer_Complaints!J:J,"Yes") -> 248 | F2: =E2/B2 -> 0.2326454 | G2: =IFERROR(ROUND(AVERAGEIFS(Consumer_Complaints!L:L,Consumer_Complaints!B:B,Table1[[#This Row],[Company]],Consumer_Complaints!L:L,">0"),0),"No Delay") -> 21
A3: Wells Fargo & Company | B3: =COUNTIF(Consumer_Complaints!A:B,Report_Task3!A3) -> 947 | C3: =COUNTIFS(Consumer_Complaints!B:B,Report_Task3!A3,Consumer_Complaints!I:I,"No") -> 21 | D3: =C3/B3 -> 0.02217529 | E3: =COUNTIFS(Consumer_Complaints!B:B,Report_Task3!A3,Consumer_Complaints!J:J,"Yes") -> 221 | F3: =E3/B3 -> 0.23336853 | G3: =IFERROR(ROUND(AVERAGEIFS(Consumer_Complaints!L:L,Consumer_Complaints!B:B,Table1[[#This Row],[Company]],Consumer_Complaints!L:L,">0"),0),"No Delay") -> 18
A4: JPMorgan Chase & Co. | B4: =COUNTIF(Consumer_Complaints!A:B,Report_Task3!A4) -> 877 | C4: =COUNTIFS(Consumer_Complaints!B:B,Report_Task3!A4,Consumer_Complaints!I:I,"No") -> 1 | D4: =C4/B4 -> 0.0011402509 | E4: =COUNTIFS(Consumer_Complaints!B:B,Report_Task3!A4,Consumer_Complaints!J:J,"Yes") -> 239 | F4: =E4/B4 -> 0.27251995 | G4: =IFERROR(ROUND(AVERAGEIFS(Consumer_Complaints!L:L,Consumer_Complaints!B:B,Table1[[#This Row],[Company]],Consumer_Complaints!L:L,">0"),0),"No Delay") -> 21
A5: Citibank | B5: =COUNTIF(Consumer_Complaints!A:B,Report_Task3!A5) -> 764 | C5: =COUNTIFS(Consumer_Complaints!B:B,Report_Task3!A5,Consumer_Complaints!I:I,"No") -> 1 | D5: =C5/B5 -> 0.0013089005 | E5: =COUNTIFS(Consumer_Complaints!B:B,Report_Task3!A5,Consumer_Complaints!J:J,"Yes") -> 152 | F5: =E5/B5 -> 0.19895288 | G5: =IFERROR(ROUND(AVERAGEIFS(Consumer_Complaints!L:L,Consumer_Complaints!B:B,Table1[[#This Row],[Company]],Consumer_Complaints!L:L,">0"),0),"No Delay") -> 21
A6: Equifax | B6: =COUNTIF(Consumer_Complaints!A:B,Report_Task3!A6) -> 531 | C6: =COUNTIFS(Consumer_Complaints!B:B,Report_Task3!A6,Consumer_Complaints!I:I,"No") -> 0 | D6: =C6/B6 -> 0 | E6: =COUNTIFS(Consumer_Complaints!B:B,Report_Task3!A6,Consumer_Complaints!J:J,"Yes") -> 133 | F6: =E6/B6 -> 0.25047081 | G6: =IFERROR(ROUND(AVERAGEIFS(Consumer_Complaints!L:L,Consumer_Complaints!B:B,Table1[[#This Row],[Company]],Consumer_Complaints!L:L,">0"),0),"No Delay") -> 22
A7: Capital One | B7: =COUNTIF(Consumer_Complaints!A:B,Report_Task3!A7) -> 458 | C7: =COUNTIFS(Consumer_Complaints!B:B,Report_Task3!A7,Consumer_Complaints!I:I,"No") -> 3 | D7: =C7/B7 -> 0.0065502183 | E7: =COUNTIFS(Consumer_Complaints!B:B,Report_Task3!A7,Consumer_Complaints!J:J,"Yes") -> 72 | F7: =E7/B7 -> 0.15720524 | G7: =IFERROR(ROUND(AVERAGEIFS(Consumer_Complaints!L:L,Consumer_Complaints!B:B,Table1[[#This Row],[Company]],Consumer_Complaints!L:L,">0"),0),"No Delay") -> 17
A8: Experian | B8: =COUNTIF(Consumer_Complaints!A:B,Report_Task3!A8) -> 456 | C8: =COUNTIFS(Consumer_Complaints!B:B,Report_Task3!A8,Consumer_Complaints!I:I,"No") -> 0 | D8: =C8/B8 -> 0 | E8: =COUNTIFS(Consumer_Complaints!B:B,Report_Task3!A8,Consumer_Complaints!J:J,"Yes") -> 59 | F8: =E8/B8 -> 0.12938596 | G8: =IFERROR(ROUND(AVERAGEIFS(Consumer_Complaints!L:L,Consumer_Complaints!B:B,Table1[[#This Row],[Company]],Consumer_Complaints!L:L,">0"),0),"No Delay") -> 19
A9: Ocwen | B9: =COUNTIF(Consumer_Complaints!A:B,Report_Task3!A9) -> 437 | C9: =COUNTIFS(Consumer_Complaints!B:B,Report_Task3!A9,Consumer_Complaints!I:I,"No") -> 11 | D9: =C9/B9 -> 0.025171625 | E9: =COUNTIFS(Consumer_Complaints!B:B,Report_Task3!A9,Consumer_Complaints!J:J,"Yes") -> 126 | F9: =E9/B9 -> 0.28832952 | G9: =IFERROR(ROUND(AVERAGEIFS(Consumer_Complaints!L:L,Consumer_Complaints!B:B,Table1[[#This Row],[Company]],Consumer_Complaints!L:L,">0"),0),"No Delay") -> 20
A10: Navient Solutions, Inc. | B10: =COUNTIF(Consumer_Complaints!A:B,Report_Task3!A10) -> 350 | C10: =COUNTIFS(Consumer_Complaints!B:B,Report_Task3!A10,Consumer_Complaints!I:I,"No") -> 0 | D10: =C10/B10 -> 0 | E10: =COUNTIFS(Consumer_Complaints!B:B,Report_Task3!A10,Consumer_Complaints!J:J,"Yes") -> 75 | F10: =E10/B10 -> 0.21428571 | G10: =IFERROR(ROUND(AVERAGEIFS(Consumer_Complaints!L:L,Consumer_Complaints!B:B,Table1[[#This Row],[Company]],Consumer_Complaints!L:L,">0"),0),"No Delay") -> 21
A11: U.S. Bancorp | B11: =COUNTIF(Consumer_Complaints!A:B,Report_Task3!A11) -> 309 | C11: =COUNTIFS(Consumer_Complaints!B:B,Report_Task3!A11,Consumer_Complaints!I:I,"No") -> 1 | D11: =C11/B11 -> 0.003236246 | E11: =COUNTIFS(Consumer_Complaints!B:B,Report_Task3!A11,Consumer_Complaints!J:J,"Yes") -> 63 | F11: =E11/B11 -> 0.2038835 | G11: =IFERROR(ROUND(AVERAGEIFS(Consumer_Complaints!L:L,Consumer_Complaints!B:B,Table1[[#This Row],[Company]],Consumer_Complaints!L:L,">0"),0),"No Delay") -> 14
A12: TransUnion Intermediate Holdings, Inc. | B12: =COUNTIF(Consumer_Complaints!A:B,Report_Task3!A12) -> 302 | C12: =COUNTIFS(Consumer_Complaints!B:B,Report_Task3!A12,Consumer_Complaints!I:I,"No") -> 0 | D12: =C12/B12 -> 0 | E12: =COUNTIFS(Consumer_Complaints!B:B,Report_Task3!A12,Consumer_Complaints!J:J,"Yes") -> 66 | F12: =E12/B12 -> 0.21854305 | G12: =IFERROR(ROUND(AVERAGEIFS(Consumer_Complaints!L:L,Consumer_Complaints!B:B,Table1[[#This Row],[Company]],Consumer_Complaints!L:L,">0"),0),"No Delay") -> 24
A13: Nationstar Mortgage | B13: =COUNTIF(Consumer_Complaints!A:B,Report_Task3!A13) -> 286 | C13: =COUNTIFS(Consumer_Complaints!B:B,Report_Task3!A13,Consumer_Complaints!I:I,"No") -> 0 | D13: =C13/B13 -> 0 | E13: =COUNTIFS(Consumer_Complaints!B:B,Report_Task3!A13,Consumer_Complaints!J:J,"Yes") -> 82 | F13: =E13/B13 -> 0.28671329 | G13: =IFERROR(ROUND(AVERAGEIFS(Consumer_Complaints!L:L,Consumer_Complaints!B:B,Table1[[#This Row],[Company]],Consumer_Complaints!L:L,">0"),0),"No Delay") -> 22
... A1051: ZestFinance | B1051: =COUNTIF(Consumer_Complaints!A:B,Report_Task3!A1051) -> 1 | C1051: =COUNTIFS(Consumer_Complaints!B:B,Report_Task3!A1051,Consumer_Complaints!I:I,"No") -> 1 | D1051: =C1051/B1051 -> 1 | E1051: =COUNTIFS(Consumer_Complaints!B:B,Report_Task3!A1051,Consumer_Complaints!J:J,"Yes") -> 0 | F1051: =E1051/B1051 -> 0 | G1051: =IFERROR(ROUND(AVERAGEIFS(Consumer_Complaints!L:L,Consumer_Complaints!B:B,Table1[[#This Row],[Company]],Consumer_Complaints!L:L,">0"),0),"No Delay") -> 5

Sheet Task 4
B3: Task 4: Reporting - Create a report with following details.
B4: 1. Top five companies with maximum number of complaints along with count of complaints
B5: 2. Top five issues with maximum number of complaints along with count of complaints
B6: 3. Monthly trends of the number of complaints in form of line / area chart
B8: Notes:
B9: 1. Add a new worksheet and name it Report_Task4 to create the above report and share your inference.

Sheet Report_Task4
A1: 1. Top five companies with maximum number of complaints along with count of complaints
A3: Row Labels | B3: Count of Complaint ID
A4: Bank of America | B4: 1066
A5: Wells Fargo & Company | B5: 947
A6: JPMorgan Chase & Co. | B6: 877
A7: Citibank | B7: 764
A8: Equifax | B8: 531
A10: 2. Top five issues with maximum number of complaints along with count of complaints
A12: Row Labels | B12: Count of Complaint ID
A13: Loan servicing, payments, escrow account | B13: 2354
A14: Account opening, closing, or management | B14: 1047
A15: Loan modification,collection,foreclosure | B15: 883
A16: Communication tactics | B16: 814
A17: Deposits and withdrawals | B17: 618
A19: 3. Monthly trends of the number of complaints in form of line / area chart
A20: Monthly Trend
A21: Count of Complaint ID | B21: Column Labels
A22: Row Labels | B22: 2013 | C22: 2014 | D22: 2015 | E22: 2016
A23: Jan | B23: 196 | C23: 283 | D23: 347 | E23: 362
A24: Feb | B24: 194 | C24: 280 | D24: 341 | E24: 349
A25: Mar | B25: 210 | C25: 324 | D25: 336 | E25: 404
A26: Apr | B26: 197 | C26: 299 | D26: 374 | E26: 386
A27: May | B27: 183 | C27: 302 | D27: 348 | E27: 357
A28: Jun | B28: 185 | C28: 280 | D28: 373 | E28: 418
A29: Jul | B29: 206 | C29: 296 | D29: 419 | E29: 421
A30: Aug | B30: 258 | C30: 308 | D30: 399 | E30: 384
A31: Sep | B31: 223 | C31: 272 | D31: 392 | E31: 214
A32: Oct | B32: 241 | C32: 335 | D32: 446 | E32: 153
A33: Nov | B33: 217 | C33: 240 | D33: 309 | E33: 99
A34: Dec | B34: 187 | C34: 253 | D34: 289 | E34: 111

Sheet Task 5
B3: Task 5: Dashboard - Create a view with following details on the year level
B4: 1. Get the following KPIs
B5: i. Total number of complaints registered in percentage with YoY change in the numbers?
B6: ii. Number of complaints for which timely response was given . What is the YoY change in the numbers?
B7: iii. Average resolution time for the complaints. What is the YoY change in the numbers?
B8: 2. Proportion of the # of complaints by different products
B9: 3. Proportion of the # of complaints by different channels which were used to file the complaint
B10: 4. There is a limited bandwidth to look in all the complaints / issues raised by customers. Display graphically which complaints should be taken on priority ?
B11: 5. Monthly trend of the number of complaints in form of line / area chart
B14: Notes:
B15: 1. Add a new worksheet and name it Report_Task5 to create the above dashboard.
B16: 2. Submit the case study by giving your key takeaways from the analysis done in task 5

Sheet Report_Task5
A1: Consumer Complaint Analysis
AD3: Total number of complaints | AE3: Count of Complaint ID | AJ3: Complaints | AK3: No. of Complaints | AN3: Count of Complaint ID | AO3: Column Labels
AD4: 2013 | AE4: 0.17835714 | AJ4: Account opening, closing, or management | AK4: 1047 | AN4: Row Labels | AO4: 2013 | AP4: 2014 | AQ4: 2015 | AR4: 2016
AD5: 2014 | AE5: 0.248 | AJ5: Account terms and changes | AK5: 18 | AN5: Jan | AO5: 196 | AP5: 283 | AQ5: 347 | AR5: 362
AD6: 2015 | AE6: 0.31235714 | AJ6: Adding money | AK6: 5 | AN6: Feb | AO6: 194 | AP6: 280 | AQ6: 341 | AR6: 349
AD7: 2016 | AE7: 0.26128571 | AJ7: Advertising and marketing | AK7: 100 | AN7: Mar | AO7: 210 | AP7: 324 | AQ7: 336 | AR7: 404
AJ8: Advertising, marketing or disclosures | AK8: 1 | AN8: Apr | AO8: 197 | AP8: 299 | AQ8: 374 | AR8: 386
AJ9: Application processing delay | AK9: 14 | AN9: May | AO9: 183 | AP9: 302 | AQ9: 348 | AR9: 357
AJ10: Application, originator, mortgage broker | AK10: 535 | AN10: Jun | AO10: 185 | AP10: 280 | AQ10: 373 | AR10: 418
AD11: Count of Complaint ID | AE11: Column Labels | AJ11: Applied for loan/did not receive money | AK11: 11 | AN11: Jul | AO11: 206 | AP11: 296 | AQ11: 419 | AR11: 421
AD12: Time Response? | AE12: 2013 | AF12: 2014 | AG12: 2015 | AH12: 2016 | AJ12: APR or interest rate | AK12: 126 | AN12: Aug | AO12: 258 | AP12: 308 | AQ12: 399 | AR12: 384
AD13: Yes | AE13: 2486 | AF13: 3424 | AG13: 4269 | AH13: 3596 | AJ13: Arbitration | AK13: 11 | AN13: Sep | AO13: 223 | AP13: 272 | AQ13: 392 | AR13: 214
AJ14: Balance transfer | AK14: 28 | AN14: Oct | AO14: 241 | AP14: 335 | AQ14: 446 | AR14: 153
AJ15: Balance transfer fee | AK15: 5 | AN15: Nov | AO15: 217 | AP15: 240 | AQ15: 309 | AR15: 99
AE16: Column Labels | AJ16: Bankruptcy | AK16: 15 | AN16: Dec | AO16: 187 | AP16: 253 | AQ16: 289 | AR16: 111
AE17: 2013 | AF17: 2014 | AG17: 2015 | AH17: 2016 | AJ17: Billing disputes | AK17: 447
AD18: Average of Resolution_Time | AE18: 11.672407 | AF18: 8.5236175 | AG18: 6.7447976 | AH18: 6.516129 | AJ18: Billing statement | AK18: 83
AJ19: Can't contact lender | AK19: 31
AJ20: Can't repay my loan | AK20: 209
AD21: Count of Complaint ID | AE21: Column Labels | AJ21: Can't stop charges to bank account | AK21: 18
AD22: Row Labels | AE22: 2013 | AF22: 2014 | AG22: 2015 | AH22: 2016 | AJ22: Cash advance | AK22: 8
AD23: Bank account or service | AE23: 551 | AF23: 500 | AG23: 759 | AH23: 619 | AJ23: Cash advance fee | AK23: 4
AD24: Consumer Loan | AE24: 121 | AF24: 227 | AG24: 294 | AH24: 235 | AJ24: Charged bank acct wrong day or amt | AK24: 5
AD25: Credit card | AE25: 484 | AF25: 458 | AG25: 625 | AH25: 569 | AJ25: Charged fees or interest I didn't expect | AK25: 90
AD26: Credit reporting | AE26: 212 | AF26: 292 | AG26: 397 | AH26: 410 | AJ26: Closing/Cancelling account | AK26: 189
AD27: Debt collection | AE27: 227 | AF27: 898 | AG27: 915 | AH27: 712 | AJ27: Collection debt dispute | AK27: 10
AD28: Money transfers | AE28: 13 | AF28: 32 | AG28: 55 | AH28: 31 | AJ28: Collection practices | AK28: 16
AD29: Mortgage | AE29: 754 | AF29: 823 | AG29: 1011 | AH29: 758 | AJ29: Communication tactics | AK29: 814
AD30: Other financial service | AF30: 1 | AG30: 8 | AH30: 15 | AJ30: Convenience checks | AK30: 4
AD31: Payday loan | AE31: 5 | AF31: 61 | AG31: 63 | AH31: 50 | AJ31: Credit card protection / Debt protection | AK31: 80
AD32: Prepaid card | AF32: 8 | AG32: 57 | AH32: 27 | AJ32: Credit decision / Underwriting | AK32: 175
AD33: Student loan | AE33: 130 | AF33: 172 | AG33: 188 | AH33: 232 | AJ33: Credit determination | AK33: 86
AD34: Virtual currency | AG34: 1 | AJ34: Credit line increase/decrease | AK34: 68
AJ35: Credit monitoring or identity protection | AK35: 146
AJ36: Credit reporting | AK36: 23
AD37: Count of Complaint ID | AE37: Column Labels | AJ37: Credit reporting company's investigation | AK37: 574
AD38: Row Labels | AE38: 2013 | AF38: 2014 | AG38: 2015 | AH38: 2016 | AJ38: Customer service / Customer relations | AK38: 97
AD39: Email | AE39: 505 | AF39: 402 | AG39: 423 | AH39: 434 | AJ39: Customer service/Customer relations | AK39: 6
AD40: Fax | AE40: 35 | AF40: 27 | AG40: 30 | AH40: 30 | AJ40: Dealing with my lender or servicer | AK40: 369
AD41: Phone | AE41: 262 | AF41: 246 | AG41: 323 | AH41: 250 | AJ41: Delinquent account | AK41: 104
AD42: Postal mail | AE42: 147 | AF42: 125 | AG42: 133 | AH42: 161 | AJ42: Deposits and withdrawals | AK42: 618
AD43: Web | AE43: 1548 | AF43: 2672 | AG43: 3464 | AH43: 2783 | AJ43: Disclosures | AK43: 2
AJ44: False statements or representation | AK44: 423
AJ45: Fees | AK45: 5
AJ46: Forbearance / Workout plans | AK46: 14
AJ47: Fraud or scam | AK47: 99
AJ48: Getting a loan | AK48: 30
AJ49: Identity theft / Fraud / Embezzlement | AK49: 212
AJ50: Improper contact or sharing of info | AK50: 354
AJ51: Improper use of my credit report | AK51: 199
AJ52: Incorrect exchange rate | AK52: 2
AJ53: Incorrect/missing disclosures or info | AK53: 7
AJ54: Late fee | AK54: 80
AJ55: Lender repossessed or sold the vehicle | AK55: 2
... AJ84: Wrong amount charged or received | AK84: 14
